conixsubscriber/__init__.py
conixsubscriber/conixsubscriber.py
conixsubscriber-0.0.3.dist-info/METADATA
conixsubscriber-0.0.3.dist-info/RECORD
conixsubscriber-0.0.3.dist-info/WHEEL
conixsubscriber-0.0.3.dist-info/top_level.txt
