Metadata-Version: 2.1
Name: conixsubscriber
Version: 0.0.3
Summary: Interface to a conix administrative domain on the subscriber side
Home-page: https://github.com/conix-center/smart-cities-demo/tree/master/client-library/subscriber/python/
Author: Joshua Adkins
Author-email: adkins@berkeley.edu
License: UNKNOWN
Keywords: sample setuptools development access control post sensor data
Platform: UNKNOWN
Requires-Dist: pint
Requires-Dist: aenum
Requires-Dist: wavemqtt
